volatility/__init__.py
volatility/addrspace.py
volatility/cache.py
volatility/commands.py
volatility/conf.py
volatility/constants.py
volatility/debug.py
volatility/dwarf.py
volatility/exceptions.py
volatility/fmtspec.py
volatility/obj.py
volatility/poolscan.py
volatility/protos.py
volatility/registry.py
volatility/scan.py
volatility/timefmt.py
volatility/utils.py
volatility/validity.py
volatility/plugins/__init__.py
volatility/plugins/bigpagepools.py
volatility/plugins/bioskbd.py
volatility/plugins/cmdline.py
volatility/plugins/common.py
volatility/plugins/connections.py
volatility/plugins/connscan.py
volatility/plugins/crashinfo.py
volatility/plugins/dlldump.py
volatility/plugins/drivermodule.py
volatility/plugins/dumpcerts.py
volatility/plugins/dumpfiles.py
volatility/plugins/envars.py
volatility/plugins/evtlogs.py
volatility/plugins/fileparam.py
volatility/plugins/filescan.py
volatility/plugins/getservicesids.py
volatility/plugins/getsids.py
volatility/plugins/handles.py
volatility/plugins/heaps.py
volatility/plugins/hibinfo.py
volatility/plugins/hpakinfo.py
volatility/plugins/iehistory.py
volatility/plugins/imagecopy.py
volatility/plugins/imageinfo.py
volatility/plugins/joblinks.py
volatility/plugins/kdbgscan.py
volatility/plugins/kpcrscan.py
volatility/plugins/machoinfo.py
volatility/plugins/mbrparser.py
volatility/plugins/mftparser.py
volatility/plugins/moddump.py
volatility/plugins/modscan.py
volatility/plugins/modules.py
volatility/plugins/multiscan.py
volatility/plugins/netscan.py
volatility/plugins/notepad.py
volatility/plugins/objtypescan.py
volatility/plugins/patcher.py
volatility/plugins/patchguard.py
volatility/plugins/pooltracker.py
volatility/plugins/privileges.py
volatility/plugins/procdump.py
volatility/plugins/pstree.py
volatility/plugins/raw2dmp.py
volatility/plugins/sockets.py
volatility/plugins/sockscan.py
volatility/plugins/ssdt.py
volatility/plugins/strings.py
volatility/plugins/taskmods.py
volatility/plugins/tcaudit.py
volatility261-2.6.2.dist-info/AUTHORS.txt
volatility261-2.6.2.dist-info/LICENSE.txt
volatility261-2.6.2.dist-info/METADATA
volatility261-2.6.2.dist-info/WHEEL
volatility261-2.6.2.dist-info/top_level.txt
volatility261-2.6.2.dist-info/RECORD
