Metadata-Version: 2.1
Name: volatility261
Version: 2.6.2
Summary: Volatility -- Volatile memory framework
Home-page: http://www.volatilityfoundation.org
Author: AAron Walters
Author-email: awalters@4tphi.net
License: GPL
Platform: UNKNOWN
Requires-Dist: distorm3 (>=3.4.1)
